fabric_rti_mcp/__init__.py
fabric_rti_mcp/_version.py
fabric_rti_mcp/common.py
fabric_rti_mcp/server.py
fabric_rti_mcp/authentication/auth_middleware.py
fabric_rti_mcp/authentication/token_obo_exchanger.py
fabric_rti_mcp/config/obo_config.py
fabric_rti_mcp/eventstream/__init__.py
fabric_rti_mcp/eventstream/eventstream_connection.py
fabric_rti_mcp/eventstream/eventstream_service.py
fabric_rti_mcp/eventstream/eventstream_tools.py
fabric_rti_mcp/kusto/__init__.py
fabric_rti_mcp/kusto/kusto_config.py
fabric_rti_mcp/kusto/kusto_connection.py
fabric_rti_mcp/kusto/kusto_formatter.py
fabric_rti_mcp/kusto/kusto_service.py
fabric_rti_mcp/kusto/kusto_tools.py
microsoft_fabric_rti_mcp-0.2.0.dist-info/licenses/LICENSE
microsoft_fabric_rti_mcp-0.2.0.dist-info/METADATA
microsoft_fabric_rti_mcp-0.2.0.dist-info/WHEEL
microsoft_fabric_rti_mcp-0.2.0.dist-info/entry_points.txt
microsoft_fabric_rti_mcp-0.2.0.dist-info/top_level.txt
microsoft_fabric_rti_mcp-0.2.0.dist-info/RECORD
