Metadata-Version: 2.4
Name: microsoft-fabric-rti-mcp
Version: 0.2.0
Summary: Microsoft Fabric RTI MCP
License-Expression: MIT
Project-URL: Homepage, https://github.com/microsoft/fabric-rti-mcp
Project-URL: Repository, https://github.com/microsoft/fabric-rti-mcp
Project-URL: Issues, https://github.com/microsoft/fabric-rti-mcp/issues
Project-URL: Documentation, https://github.com/microsoft/fabric-rti-mcp#readme
Classifier: Programming Language :: Python :: 3.10
Classifier: Programming Language :: Python :: 3.11
Classifier: Programming Language :: Python :: 3.12
Classifier: Operating System :: OS Independent
Classifier: Development Status :: 2 - Pre-Alpha
Requires-Python: >=3.10
License-File: LICENSE
Requires-Dist: httpx~=0.28.1
Requires-Dist: fastmcp~=2.5.0
Requires-Dist: azure-kusto-data~=5.0.0
Requires-Dist: azure-identity~=1.23.0
Requires-Dist: azure-kusto-ingest~=5.0.0
Requires-Dist: msal~=1.32.0
Provides-Extra: dev
Requires-Dist: black>=23.0.0; extra == "dev"
Requires-Dist: isort>=5.12.0; extra == "dev"
Requires-Dist: flake8>=6.0.0; extra == "dev"
Requires-Dist: mypy>=1.0.0; extra == "dev"
Requires-Dist: pytest>=7.0.0; extra == "dev"
Dynamic: license-file
